haram/__init__.py
haram-1.0.1.dist-info/LICENSE
haram-1.0.1.dist-info/METADATA
haram-1.0.1.dist-info/WHEEL
haram-1.0.1.dist-info/RECORD
