Metadata-Version: 2.3
Name: haram
Version: 1.0.1
Summary: The Haram Principles of Python
License: Unlicense
Author: Petar Poposki
Author-email: petar@halicea.com
Requires-Python: >=3.13
Classifier: Programming Language :: Python :: 3
Classifier: Programming Language :: Python :: 3.13
Classifier: License :: OSI Approved :: The Unlicense (Unlicense)
Classifier: Operating System :: OS Independent
